velocity_py/__init__.py
velocity_py/main.py
velocity_py-0.2.4.dist-info/METADATA
velocity_py-0.2.4.dist-info/WHEEL
velocity_py-0.2.4.dist-info/entry_points.txt
velocity_py-0.2.4.dist-info/licenses/LICENSE
velocity_py-0.2.4.dist-info/RECORD
