Metadata-Version: 2.4
Name: velocity-py
Version: 0.2.4
Summary: A high-performance scaffolding tool for strictly typed Python projects.
Author-email: Zakhar Aleksandruk <aleksandrukzakhar@icloud.com>
License-File: LICENSE
Requires-Python: >=3.9
Requires-Dist: questionary>=2.0.0
Requires-Dist: rich>=13.0.0
Requires-Dist: typer>=0.9.0
